diffusion/DDMFunctions.py
diffusion/Network.py
diffusion/Scheduler.py
diffusion/Test.py
diffusion/Train.py
diffusion/__init__.py
diffusion/diffusion_process.py
Denoising_Diffusion_Probabilistic_Models-1.0.2.dist-info/METADATA
Denoising_Diffusion_Probabilistic_Models-1.0.2.dist-info/WHEEL
Denoising_Diffusion_Probabilistic_Models-1.0.2.dist-info/top_level.txt
Denoising_Diffusion_Probabilistic_Models-1.0.2.dist-info/RECORD
