Metadata-Version: 2.1
Name: Denoising-Diffusion-Probabilistic-Models
Version: 1.0.2
Summary: Denoising Diffusion Probabilistic Models
Author: Michiyasu Uchiyama
License: MIT
Keywords: c
Classifier: License :: OSI Approved :: MIT License
Classifier: Programming Language :: Python :: 3.10
